{"raceId":"pmu:15032018/R3/C8","raceNumber":8,"reunionNumber":3,"raceScheduledStartEpochMs":1521127200000,"raceName":"CRITERIUM DE TROT DE LYON- PX PARIS-TURF","distance":2600,"duration":204490,"ropeSide":"LEFT","fieldType":"POUZZOLANE","raceCategory":"HARNESS","sexCategory":"ALL","price":{"total":35000,"first":15750,"fifth":1750},"hippodromeName":"LYON-PARILLY","fieldQuality":"NO_FIELD_QUALITY","photoFinishes":[{"height":217,"width":450,"url":"https://www.pmu.fr/infocentre/infocentre/photos/arrivee/15032018R3C8/photo_arrivee_450px_width_size.jpg","originalSize":false},{"height":96,"width":200,"url":"https://www.pmu.fr/infocentre/infocentre/photos/arrivee/15032018R3C8/photo_arrivee_200px_width_size.jpg","originalSize":false},{"height":230,"width":478,"url":"https://www.pmu.fr/infocentre/infocentre/photos/arrivee/15032018R3C8/photo_arrivee_original_size.jpg","originalSize":true}],"startType":"AUTOSTART","raceType":"CLASS_B","humanDescription":"CRITERIUM DE TROT DE LYON Course  8 Course B Départ à l'Autostart 35.000. - Attelé. - 2.600 mètres. 15.750, 8.750, 4.900, 2.800, 1.750, 700, 350.- alloués par la S.E.C.F. Pour 6 à 10 ans inclus, n'ayant pas gagné 400.000. Sont seules admises à driver les personnes ayant gagné au moins cinq courses (en étant titulaire d'une autorisation de monter à titre professionnel).","nonPartants":[],"partants":[{"raceId":"pmu_race:15032018/R3/C8","horse":{"name":"AVRIK DE GUEZ","pmuName":"AVRIK DE GUEZ","genyName":"AVRIK DE GUEZ","genyId":2331929,"canalturfName":"AVRIK DE GUEZ","canalturfId":142767},"hasSulky":true,"age":8,"partantNum":1,"breed":"TROTTEUR FRANCAIS","ropePlace":1,"sex":"H","blinkers":"NONE","ownerName":"Ecurie J.PH. DUCHER","trainer":{"name":"J.PH. DUCHER","pmuName":"J.PH. DUCHER","genyName":"Jean-Philippe Ducher","canalturfId":551,"canalturfName":"J.PH. DUCHER"},"raiserName":"M. René GUEZILLE","allure":"TROT","horseshoe":"ALL","jockey":{"name":"J.PH. DUCHER","pmuName":"J.PH. DUCHER","genyName":"Jean-Philippe Ducher","canalturfName":"J.-P. DUCHER","canalturfId":10960},"robe":"021_BAI F.","musique":"0a(17)6aDaDa4a8a6a1a1a","pregnant":false,"stats":{"firstRace":false,"numberRaces":55,"wonRaces":16,"places":21,"secondPlaces":2,"thirdPlaces":4,"earnMoneyTotal":27276000,"earnMoneyFirst":21780000,"earnMoneyPlaced":5496000,"earnMoneyCurrentYear":0,"earnMoneyPreviousYear":7085000},"ecurieId":"pmu/ecurie/15032018/R3/C8:undefined","pedigree":{"father":"JOKER DE ROZOY","mother":"QUOUMBAYA DE GUEZ"},"distance":2600,"engagement":false,"weightBeforeChanged":false,"supplement":0,"results":{"event":"NONE","position":9,"totalTimeMs":206140,"kmReducedMs":79300},"odds":{"pmu":{"lastDirect":{"typeBet":"PMU_E_SIMPLE_GAGNANT","ratio":78,"typeRatio":"DIRECT","tendancyNumber":0,"epochMs":1521127403000,"permutation":1,"favorite":false,"grossePrise":false},"lastReference":{"typeBet":"PMU_E_SIMPLE_GAGNANT","ratio":42,"typeRatio":"REFERENCE","tendancyNumber":4.7,"epochMs":1521125412000,"permutation":1,"favorite":false,"grossePrise":false},"reference10h":{"ratio":42.3},"chronological":[{"ratio":78.1,"epoch":1521147300000},{"ratio":78.1,"epoch":1521147900000},{"ratio":78.1,"epoch":1521148500000},{"ratio":78.1,"epoch":1521149100000},{"ratio":78.1,"epoch":1521149700000},{"ratio":78.1,"epoch":1521150300000},{"ratio":78.1,"epoch":1521150900000},{"ratio":78.1,"epoch":1521151500000},{"ratio":78.1,"epoch":1521152100000},{"ratio":78.1,"epoch":1521152700000},{"ratio":78.1,"epoch":1521153300000},{"ratio":78.1,"epoch":1521153900000}]},"geny":{"lastDirect":{"ratio":40}},"zeturf":{"lastDirect":{"ratio":58.8}},"betclic":{"lastDirect":{"ratio":83.8}},"unibet":{"lastDirect":{"ratio":57.7}}},"casaques":[{"url":"https://turfinfo.pmucdn.fr/casaques/15032018/R3/C8/P1.png"},{"url":"https://media.genybet.fr/web/image/casaque/04/1003304_1.png"},{"url":"https://www.canalturf.com/interface/casaques/2018-03/167000.png","y":0,"width":55,"height":65}],"moneyWon":272760},{"raceId":"pmu_race:15032018/R3/C8","horse":{"name":"CLIF DU POMMEREUX","pmuName":"CLIF DU POMMEREUX","genyName":"CLIF DU POMMEREUX","genyId":2404297,"canalturfName":"CLIF DU POMMEREUX","canalturfId":177143},"hasSulky":true,"age":6,"partantNum":2,"breed":"TROTTEUR FRANCAIS","ropePlace":2,"sex":"M","blinkers":"NONE","ownerName":"N. LOLIC","trainer":{"name":"S. ROGER","pmuName":"S. ROGER","genyName":"Sylvain Roger","canalturfId":390,"canalturfName":"S. ROGER"},"raiserName":"M. Noël LOLIC","allure":"TROT","horseshoe":"ANT","jockey":{"name":"J.F. SENET","pmuName":"J.F. SENET","genyName":"Jean-François Senet","canalturfName":"J.-F. SENET","canalturfId":207},"robe":"020_BAI","musique":"6a6a0aDa(17)9aDaDa2a2a","pregnant":false,"stats":{"firstRace":false,"numberRaces":42,"wonRaces":4,"places":26,"secondPlaces":8,"thirdPlaces":7,"earnMoneyTotal":38773000,"earnMoneyFirst":9090000,"earnMoneyPlaced":29683000,"earnMoneyCurrentYear":384000,"earnMoneyPreviousYear":8880000},"ecurieId":"pmu/ecurie/15032018/R3/C8:A","pedigree":{"father":"LOVE YOU","mother":"NOUNE DU POMMEREUX"},"distance":2600,"engagement":false,"weightBeforeChanged":false,"supplement":0,"results":{"event":"NONE","position":3,"totalTimeMs":204850,"kmReducedMs":78800},"odds":{"pmu":{"lastDirect":{"typeBet":"PMU_E_SIMPLE_GAGNANT","ratio":5.7,"typeRatio":"DIRECT","tendancyNumber":0,"epochMs":1521127403000,"permutation":1,"favorite":false,"grossePrise":false},"lastReference":{"typeBet":"PMU_E_SIMPLE_GAGNANT","ratio":6.4,"typeRatio":"REFERENCE","tendancyNumber":6.66,"epochMs":1521125412000,"permutation":1,"favorite":false,"grossePrise":false},"reference10h":{"ratio":6.4},"chronological":[{"ratio":5.7,"epoch":1521147300000},{"ratio":5.7,"epoch":1521147900000},{"ratio":5.7,"epoch":1521148500000},{"ratio":5.7,"epoch":1521149100000},{"ratio":5.7,"epoch":1521149700000},{"ratio":5.7,"epoch":1521150300000},{"ratio":5.7,"epoch":1521150900000},{"ratio":5.7,"epoch":1521151500000},{"ratio":5.7,"epoch":1521152100000},{"ratio":5.7,"epoch":1521152700000},{"ratio":5.7,"epoch":1521153300000},{"ratio":5.7,"epoch":1521153900000}]},"geny":{"lastDirect":{"ratio":6}},"zeturf":{"lastDirect":{"ratio":6.8}},"betclic":{"lastDirect":{"ratio":11}},"unibet":{"lastDirect":{"ratio":6.6}}},"casaques":[{"url":"https://turfinfo.pmucdn.fr/casaques/15032018/R3/C8/P2.png"},{"url":"https://media.genybet.fr/web/image/casaque/94/1006694_1.png"},{"url":"https://www.canalturf.com/interface/casaques/2018-03/167000.png","y":65,"width":55,"height":65}],"moneyWon":387730},{"raceId":"pmu_race:15032018/R3/C8","horse":{"name":"VIC DU POMMEREUX","pmuName":"VIC DU POMMEREUX","genyName":"VIC DU POMMEREUX","genyId":2235646,"canalturfName":"VIC DU POMMEREUX","canalturfId":106925},"hasSulky":true,"age":9,"partantNum":3,"breed":"TROTTEUR FRANCAIS","ropePlace":3,"sex":"M","blinkers":"NONE","ownerName":"N. LOLIC","trainer":{"name":"S. ROGER","pmuName":"S. ROGER","genyName":"Sylvain Roger","canalturfId":390,"canalturfName":"S. ROGER"},"raiserName":"M. Noël LOLIC","allure":"TROT","horseshoe":"NONE","jockey":{"name":"D. BEKAERT","pmuName":"D. BEKAERT","genyName":"David Békaert","canalturfName":"D. BEKAERT","canalturfId":1134},"robe":"020_BAI","musique":"8a0a3aDa(17)9a0a0a0a9a","pregnant":false,"stats":{"firstRace":false,"numberRaces":102,"wonRaces":9,"places":52,"secondPlaces":9,"thirdPlaces":9,"earnMoneyTotal":37050000,"earnMoneyFirst":16100000,"earnMoneyPlaced":20950000,"earnMoneyCurrentYear":770000,"earnMoneyPreviousYear":6369000},"ecurieId":"pmu/ecurie/15032018/R3/C8:A","pedigree":{"father":"LOVE YOU","mother":"KUBRUNE"},"distance":2600,"engagement":false,"weightBeforeChanged":false,"supplement":0,"results":{"event":"NONE","position":4,"totalTimeMs":205250,"kmReducedMs":78900},"odds":{"pmu":{"lastDirect":{"typeBet":"PMU_E_SIMPLE_GAGNANT","ratio":21,"typeRatio":"DIRECT","tendancyNumber":0,"epochMs":1521127403000,"permutation":1,"favorite":false,"grossePrise":false},"lastReference":{"typeBet":"PMU_E_SIMPLE_GAGNANT","ratio":22,"typeRatio":"REFERENCE","tendancyNumber":-3.91,"epochMs":1521125412000,"permutation":1,"favorite":false,"grossePrise":false},"reference10h":{"ratio":22.1},"chronological":[{"ratio":21.9,"epoch":1521147300000},{"ratio":21.9,"epoch":1521147900000},{"ratio":21.9,"epoch":1521148500000},{"ratio":21.9,"epoch":1521149100000},{"ratio":21.9,"epoch":1521149700000},{"ratio":21.9,"epoch":1521150300000},{"ratio":21.9,"epoch":1521150900000},{"ratio":21.9,"epoch":1521151500000},{"ratio":21.9,"epoch":1521152100000},{"ratio":21.9,"epoch":1521152700000},{"ratio":21.9,"epoch":1521153300000},{"ratio":21.9,"epoch":1521153900000}]},"geny":{"lastDirect":{"ratio":7.8}},"zeturf":{"lastDirect":{"ratio":23.5}},"betclic":{"lastDirect":{"ratio":32.4}},"unibet":{"lastDirect":{"ratio":23}}},"casaques":[{"url":"https://turfinfo.pmucdn.fr/casaques/15032018/R3/C8/P3.png"},{"url":"https://media.genybet.fr/web/image/casaque/94/1006694_1.png"},{"url":"https://www.canalturf.com/interface/casaques/2018-03/167000.png","y":130,"width":55,"height":65}],"moneyWon":370500},{"raceId":"pmu_race:15032018/R3/C8","horse":{"name":"CALY LOULOU","pmuName":"CALY LOULOU","genyName":"CALY LOULOU","genyId":2402495,"canalturfName":"CALY LOULOU","canalturfId":176291},"hasSulky":true,"age":6,"partantNum":4,"breed":"TROTTEUR FRANCAIS","ropePlace":4,"sex":"F","blinkers":"NONE","ownerName":"D. BAUX","trainer":{"name":"H. CHAUVE-LAFFAY","pmuName":"H. CHAUVE-LAFFAY","genyName":"Hervé Chauve-Laffay","canalturfId":506,"canalturfName":"H. CHAUVE-LAFFAY"},"raiserName":"M. Hervé CHAUVE-LAFFAY","allure":"TROT","horseshoe":"NONE","jockey":{"name":"S. PELTIER","pmuName":"S. PELTIER","genyName":"Serge Peltier","canalturfName":"S. PELTIER","canalturfId":366},"robe":"001_ALEZAN","musique":"5a2a5a8a0a(17)2a4a5a5a","pregnant":false,"stats":{"firstRace":false,"numberRaces":44,"wonRaces":5,"places":32,"secondPlaces":8,"thirdPlaces":4,"earnMoneyTotal":35077000,"earnMoneyFirst":12495000,"earnMoneyPlaced":22582000,"earnMoneyCurrentYear":3725000,"earnMoneyPreviousYear":12977000},"ecurieId":"pmu/ecurie/15032018/R3/C8:undefined","pedigree":{"father":"GAZOUILLIS","mother":"NEIGE DE GENETINE"},"distance":2600,"engagement":false,"weightBeforeChanged":false,"supplement":0,"results":{"event":"NONE","position":2,"totalTimeMs":204830,"kmReducedMs":78800},"odds":{"pmu":{"lastDirect":{"typeBet":"PMU_E_SIMPLE_GAGNANT","ratio":2.1,"typeRatio":"DIRECT","tendancyNumber":0,"epochMs":1521127403000,"permutation":1,"favorite":true,"grossePrise":false},"lastReference":{"typeBet":"PMU_E_SIMPLE_GAGNANT","ratio":1.8,"typeRatio":"REFERENCE","tendancyNumber":0,"epochMs":1521125412000,"permutation":1,"favorite":true,"grossePrise":false},"reference10h":{"ratio":1.8},"chronological":[{"ratio":2.1,"epoch":1521147300000},{"ratio":2.1,"epoch":1521147900000},{"ratio":2.1,"epoch":1521148500000},{"ratio":2.1,"epoch":1521149100000},{"ratio":2.1,"epoch":1521149700000},{"ratio":2.1,"epoch":1521150300000},{"ratio":2.1,"epoch":1521150900000},{"ratio":2.1,"epoch":1521151500000},{"ratio":2.1,"epoch":1521152100000},{"ratio":2.1,"epoch":1521152700000},{"ratio":2.1,"epoch":1521153300000},{"ratio":2.1,"epoch":1521153900000}]},"geny":{"lastDirect":{"ratio":2.2}},"zeturf":{"lastDirect":{"ratio":1.7}},"betclic":{"lastDirect":{"ratio":1.1}},"unibet":{"lastDirect":{"ratio":1.6}}},"casaques":[{"url":"https://turfinfo.pmucdn.fr/casaques/15032018/R3/C8/P4.png"},{"url":"https://media.genybet.fr/web/image/casaque/89/1068789_1.png"},{"url":"https://www.canalturf.com/interface/casaques/2018-03/167000.png","y":195,"width":55,"height":65}],"moneyWon":350770},{"raceId":"pmu_race:15032018/R3/C8","horse":{"name":"VA TRES BIEN","pmuName":"VA TRES BIEN","genyName":"VA TRES BIEN","genyId":2262701,"canalturfName":"VA TRES BIEN","canalturfId":118581},"hasSulky":true,"age":9,"partantNum":5,"breed":"TROTTEUR FRANCAIS","ropePlace":5,"sex":"H","blinkers":"NONE","ownerName":"Mme N. BUSSET","trainer":{"name":"M. BUSSET","pmuName":"M. BUSSET","genyName":"Maxime Busset","canalturfId":526,"canalturfName":"J.-P. MONTI"},"raiserName":"M. Yves MAILET","allure":"TROT","horseshoe":"NONE","jockey":{"name":"J. BOILLEREAU","pmuName":"J. BOILLEREAU","genyName":"Suc. Jean Boillereau","canalturfName":"J. BOILLEREAU","canalturfId":390},"robe":"020_BAI","musique":"(17)7a0aDm7m4a4m6a8m3a","pregnant":false,"stats":{"firstRace":false,"numberRaces":84,"wonRaces":13,"places":38,"secondPlaces":8,"thirdPlaces":4,"earnMoneyTotal":37289000,"earnMoneyFirst":19690000,"earnMoneyPlaced":17599000,"earnMoneyCurrentYear":0,"earnMoneyPreviousYear":1878000},"ecurieId":"pmu/ecurie/15032018/R3/C8:undefined","pedigree":{"father":"NEZ PERCE","mother":"GIBOULEE DE MARS"},"distance":2600,"engagement":false,"weightBeforeChanged":false,"supplement":0,"results":{"event":"NONE","position":5,"totalTimeMs":205250,"kmReducedMs":78900},"odds":{"pmu":{"lastDirect":{"typeBet":"PMU_E_SIMPLE_GAGNANT","ratio":45,"typeRatio":"DIRECT","tendancyNumber":0,"epochMs":1521127403000,"permutation":1,"favorite":false,"grossePrise":false},"lastReference":{"typeBet":"PMU_E_SIMPLE_GAGNANT","ratio":29,"typeRatio":"REFERENCE","tendancyNumber":3.83,"epochMs":1521125412000,"permutation":1,"favorite":false,"grossePrise":false},"reference10h":{"ratio":29.8},"chronological":[{"ratio":45,"epoch":1521147300000},{"ratio":45,"epoch":1521147900000},{"ratio":45,"epoch":1521148500000},{"ratio":45,"epoch":1521149100000},{"ratio":45,"epoch":1521149700000},{"ratio":45,"epoch":1521150300000},{"ratio":45,"epoch":1521150900000},{"ratio":45,"epoch":1521151500000},{"ratio":45,"epoch":1521152100000},{"ratio":45,"epoch":1521152700000},{"ratio":45,"epoch":1521153300000},{"ratio":45,"epoch":1521153900000}]},"geny":{"lastDirect":{"ratio":54}},"zeturf":{"lastDirect":{"ratio":68.4}},"betclic":{"lastDirect":{"ratio":51.4}},"unibet":{"lastDirect":{"ratio":67.1}}},"casaques":[{"url":"https://turfinfo.pmucdn.fr/casaques/15032018/R3/C8/P5.png"},{"url":"https://media.genybet.fr/web/image/casaque/11/1001611_1.png"},{"url":"https://www.canalturf.com/interface/casaques/2018-03/167000.png","y":260,"width":55,"height":65}],"moneyWon":372890},{"raceId":"pmu_race:15032018/R3/C8","horse":{"name":"BAD BOY DU DOLLAR","pmuName":"BAD BOY DU DOLLAR","genyName":"BAD BOY DU DOLLAR","genyId":2369139,"canalturfName":"BAD BOY DU DOLLAR","canalturfId":160486},"hasSulky":true,"age":7,"partantNum":6,"breed":"TROTTEUR FRANCAIS","ropePlace":6,"sex":"M","blinkers":"NONE","ownerName":"M.A. BOUVET","trainer":{"name":"S. ROGER","pmuName":"S. ROGER","genyName":"Sylvain Roger","canalturfId":390,"canalturfName":"S. ROGER"},"raiserName":"M. Jean Luc COUPE","allure":"TROT","horseshoe":"NONE","jockey":{"name":"L. GARCIA","pmuName":"L. GARCIA","genyName":"Loris Garcia","canalturfName":"S. ROGER","canalturfId":209},"robe":"020_BAI","musique":"7a3a5a8a(17)8a5a3a7a5a","pregnant":false,"stats":{"firstRace":false,"numberRaces":60,"wonRaces":7,"places":36,"secondPlaces":10,"thirdPlaces":7,"earnMoneyTotal":37845000,"earnMoneyFirst":16290000,"earnMoneyPlaced":21555000,"earnMoneyCurrentYear":1937000,"earnMoneyPreviousYear":11880000},"ecurieId":"pmu/ecurie/15032018/R3/C8:undefined","pedigree":{"father":"MAGNIFICENT RODNEY","mother":"NYMPHE DU DOLLAR"},"distance":2600,"engagement":false,"weightBeforeChanged":false,"supplement":0,"results":{"event":"NONE","position":1,"totalTimeMs":204490,"kmReducedMs":78700},"odds":{"pmu":{"lastDirect":{"typeBet":"PMU_E_SIMPLE_GAGNANT","ratio":5.7,"typeRatio":"DIRECT","tendancyNumber":0,"epochMs":1521127403000,"permutation":1,"favorite":false,"grossePrise":false},"lastReference":{"typeBet":"PMU_E_SIMPLE_GAGNANT","ratio":7.5,"typeRatio":"REFERENCE","tendancyNumber":1.35,"epochMs":1521125412000,"permutation":1,"favorite":false,"grossePrise":false},"reference10h":{"ratio":7.5},"chronological":[{"ratio":5.7,"epoch":1521147300000},{"ratio":5.7,"epoch":1521147900000},{"ratio":5.7,"epoch":1521148500000},{"ratio":5.7,"epoch":1521149100000},{"ratio":5.7,"epoch":1521149700000},{"ratio":5.7,"epoch":1521150300000},{"ratio":5.7,"epoch":1521150900000},{"ratio":5.7,"epoch":1521151500000},{"ratio":5.7,"epoch":1521152100000},{"ratio":5.7,"epoch":1521152700000},{"ratio":5.7,"epoch":1521153300000},{"ratio":5.7,"epoch":1521153900000}]},"geny":{"lastDirect":{"ratio":7.3}},"zeturf":{"lastDirect":{"ratio":5.6}},"betclic":{"lastDirect":{"ratio":18.1}},"unibet":{"lastDirect":{"ratio":5.4}}},"casaques":[{"url":"https://turfinfo.pmucdn.fr/casaques/15032018/R3/C8/P6.png"},{"url":"https://media.genybet.fr/web/image/casaque/92/1019392_1.png"},{"url":"https://www.canalturf.com/interface/casaques/2018-03/167000.png","y":325,"width":55,"height":65}],"moneyWon":378450},{"raceId":"pmu_race:15032018/R3/C8","horse":{"name":"ARIANE DE CAPONET","pmuName":"ARIANE DE CAPONET","genyName":"ARIANE DE CAPONET","genyId":2300771,"canalturfName":"ARIANE DE CAPONET","canalturfId":130678},"hasSulky":true,"age":8,"partantNum":7,"breed":"TROTTEUR FRANCAIS","ropePlace":7,"sex":"F","blinkers":"NONE","ownerName":"R. GAJA","trainer":{"name":"H. CHAUVE-LAFFAY","pmuName":"H. CHAUVE-LAFFAY","genyName":"Hervé Chauve-Laffay","canalturfId":506,"canalturfName":"H. CHAUVE-LAFFAY"},"raiserName":"M. Laurent GABRIEL","allure":"TROT","horseshoe":"NONE","jockey":{"name":"H. CHAUVE-LAFFAY","pmuName":"H. CHAUVE-LAFFAY","genyName":"Hervé Chauve-Laffay","canalturfName":"H. CHAUVE-LAFFAY","canalturfId":362},"robe":"020_BAI","musique":"3m3m4a(17)3a4a4a1a1a5a","pregnant":false,"stats":{"firstRace":false,"numberRaces":85,"wonRaces":14,"places":56,"secondPlaces":13,"thirdPlaces":15,"earnMoneyTotal":39021000,"earnMoneyFirst":16560000,"earnMoneyPlaced":22461000,"earnMoneyCurrentYear":3510000,"earnMoneyPreviousYear":7101000},"ecurieId":"pmu/ecurie/15032018/R3/C8:undefined","pedigree":{"father":"ONE DU RIB","mother":"NAYA DE JOUDES"},"distance":2600,"engagement":false,"weightBeforeChanged":false,"supplement":0,"results":{"event":"DAI"},"odds":{"pmu":{"lastDirect":{"typeBet":"PMU_E_SIMPLE_GAGNANT","ratio":9.3,"typeRatio":"DIRECT","tendancyNumber":0,"epochMs":1521127403000,"permutation":1,"favorite":false,"grossePrise":false},"lastReference":{"typeBet":"PMU_E_SIMPLE_GAGNANT","ratio":10,"typeRatio":"REFERENCE","tendancyNumber":-1.81,"epochMs":1521125412000,"permutation":1,"favorite":false,"grossePrise":false},"reference10h":{"ratio":10.8},"chronological":[{"ratio":9.3,"epoch":1521147300000},{"ratio":9.3,"epoch":1521147900000},{"ratio":9.3,"epoch":1521148500000},{"ratio":9.3,"epoch":1521149100000},{"ratio":9.3,"epoch":1521149700000},{"ratio":9.3,"epoch":1521150300000},{"ratio":9.3,"epoch":1521150900000},{"ratio":9.3,"epoch":1521151500000},{"ratio":9.3,"epoch":1521152100000},{"ratio":9.3,"epoch":1521152700000},{"ratio":9.3,"epoch":1521153300000},{"ratio":9.3,"epoch":1521153900000}]},"geny":{"lastDirect":{"ratio":12}},"zeturf":{"lastDirect":{"ratio":13.6}},"betclic":{"lastDirect":{"ratio":28}},"unibet":{"lastDirect":{"ratio":13.3}}},"casaques":[{"url":"https://turfinfo.pmucdn.fr/casaques/15032018/R3/C8/P7.png"},{"url":"https://media.genybet.fr/web/image/casaque/78/1021778_1.png"},{"url":"https://www.canalturf.com/interface/casaques/2018-03/167000.png","y":390,"width":55,"height":65}],"moneyWon":390210},{"raceId":"pmu_race:15032018/R3/C8","horse":{"name":"CALIN DE MORGE","pmuName":"CALIN DE MORGE","genyName":"CALIN DE MORGE","genyId":2423510,"canalturfName":"CALIN DE MORGE","canalturfId":186817},"hasSulky":true,"age":6,"partantNum":8,"breed":"TROTTEUR FRANCAIS","ropePlace":8,"sex":"H","blinkers":"NONE","ownerName":"Ecurie H.D. TROT","trainer":{"name":"D. HAON","pmuName":"D. HAON","genyName":"David Haon","canalturfId":1179,"canalturfName":"D. HAON"},"raiserName":"M. Philippe BRAZIER","allure":"TROT","horseshoe":"ANT","jockey":{"name":"D. HAON","pmuName":"D. HAON","genyName":"David Haon","canalturfName":"D. HAON","canalturfId":1078},"robe":"001_ALEZAN","musique":"7a(17)7a5a1a2a3a4a5a1a","pregnant":false,"stats":{"firstRace":false,"numberRaces":43,"wonRaces":10,"places":25,"secondPlaces":6,"thirdPlaces":7,"earnMoneyTotal":28852000,"earnMoneyFirst":18045000,"earnMoneyPlaced":10807000,"earnMoneyCurrentYear":90000,"earnMoneyPreviousYear":17502000},"ecurieId":"pmu/ecurie/15032018/R3/C8:undefined","pedigree":{"father":"OZIO ROYAL","mother":"PARADISE PRINCESS"},"distance":2600,"engagement":false,"weightBeforeChanged":false,"supplement":0,"results":{"event":"NONE","position":7,"totalTimeMs":205380,"kmReducedMs":79000},"odds":{"pmu":{"lastDirect":{"typeBet":"PMU_E_SIMPLE_GAGNANT","ratio":17,"typeRatio":"DIRECT","tendancyNumber":0,"epochMs":1521127403000,"permutation":1,"favorite":false,"grossePrise":false},"lastReference":{"typeBet":"PMU_E_SIMPLE_GAGNANT","ratio":22,"typeRatio":"REFERENCE","tendancyNumber":-8.64,"epochMs":1521125412000,"permutation":1,"favorite":false,"grossePrise":false},"reference10h":{"ratio":22.2},"chronological":[{"ratio":17,"epoch":1521147300000},{"ratio":17,"epoch":1521147900000},{"ratio":17,"epoch":1521148500000},{"ratio":17,"epoch":1521149100000},{"ratio":17,"epoch":1521149700000},{"ratio":17,"epoch":1521150300000},{"ratio":17,"epoch":1521150900000},{"ratio":17,"epoch":1521151500000},{"ratio":17,"epoch":1521152100000},{"ratio":17,"epoch":1521152700000},{"ratio":17,"epoch":1521153300000},{"ratio":17,"epoch":1521153900000}]},"geny":{"lastDirect":{"ratio":13}},"zeturf":{"lastDirect":{"ratio":21.9}},"betclic":{"lastDirect":{"ratio":35.1}},"unibet":{"lastDirect":{"ratio":21.5}}},"casaques":[{"url":"https://turfinfo.pmucdn.fr/casaques/15032018/R3/C8/P8.png"},{"url":"https://media.genybet.fr/web/image/casaque/54/1038954_1.png"},{"url":"https://www.canalturf.com/interface/casaques/2018-03/167000.png","y":455,"width":55,"height":65}],"moneyWon":288520},{"raceId":"pmu_race:15032018/R3/C8","horse":{"name":"ULYSSE MARIA","pmuName":"ULYSSE MARIA","genyName":"ULYSSE MARIA","genyId":2221695,"canalturfName":"ULYSSE MARIA","canalturfId":102869},"hasSulky":true,"age":10,"partantNum":9,"breed":"TROTTEUR FRANCAIS","ropePlace":9,"sex":"H","blinkers":"NONE","ownerName":"R. BERUJAT","trainer":{"name":"R. BERUJAT","pmuName":"R. BERUJAT","genyName":"Romain Berujat","canalturfId":11636,"canalturfName":"R. BERUJAT"},"raiserName":"M. Jules PAILLARD","allure":"TROT","horseshoe":"ALL","jockey":{"name":"R. BERUJAT","pmuName":"R. BERUJAT","genyName":"Romain Berujat","canalturfName":"R. BERUJAT","canalturfId":403},"robe":"020_BAI","musique":"5a4a3a6a(17)8a7a1a0a8a","pregnant":false,"stats":{"firstRace":false,"numberRaces":67,"wonRaces":11,"places":32,"secondPlaces":7,"thirdPlaces":9,"earnMoneyTotal":23916000,"earnMoneyFirst":11395000,"earnMoneyPlaced":12521000,"earnMoneyCurrentYear":1462000,"earnMoneyPreviousYear":4520000},"ecurieId":"pmu/ecurie/15032018/R3/C8:undefined","pedigree":{"father":"NUAGE DE LAIT","mother":"KEMETCHA MARIA"},"distance":2600,"engagement":false,"weightBeforeChanged":false,"supplement":0,"results":{"event":"NONE","position":8,"totalTimeMs":205680,"kmReducedMs":79100},"odds":{"pmu":{"lastDirect":{"typeBet":"PMU_E_SIMPLE_GAGNANT","ratio":64,"typeRatio":"DIRECT","tendancyNumber":0,"epochMs":1521127403000,"permutation":1,"favorite":false,"grossePrise":false},"lastReference":{"typeBet":"PMU_E_SIMPLE_GAGNANT","ratio":46,"typeRatio":"REFERENCE","tendancyNumber":7.12,"epochMs":1521125412000,"permutation":1,"favorite":false,"grossePrise":false},"reference10h":{"ratio":46.6},"chronological":[{"ratio":64.1,"epoch":1521147300000},{"ratio":64.1,"epoch":1521147900000},{"ratio":64.1,"epoch":1521148500000},{"ratio":64.1,"epoch":1521149100000},{"ratio":64.1,"epoch":1521149700000},{"ratio":64.1,"epoch":1521150300000},{"ratio":64.1,"epoch":1521150900000},{"ratio":64.1,"epoch":1521151500000},{"ratio":64.1,"epoch":1521152100000},{"ratio":64.1,"epoch":1521152700000},{"ratio":64.1,"epoch":1521153300000},{"ratio":64.1,"epoch":1521153900000}]},"geny":{"lastDirect":{"ratio":31}},"zeturf":{"lastDirect":{"ratio":106.8}},"betclic":{"lastDirect":{"ratio":92.4}},"unibet":{"lastDirect":{"ratio":104.8}}},"casaques":[{"url":"https://turfinfo.pmucdn.fr/casaques/15032018/R3/C8/P9.png"},{"url":"https://media.genybet.fr/web/image/casaque/78/1000878_1.png"},{"url":"https://www.canalturf.com/interface/casaques/2018-03/167000.png","y":520,"width":55,"height":65}],"moneyWon":239160},{"raceId":"pmu_race:15032018/R3/C8","horse":{"name":"UGO D'URZY","pmuName":"UGO D'URZY","genyName":"UGO D'URZY","genyId":2170894,"canalturfName":"UGO D'URZY","canalturfId":116846},"hasSulky":true,"age":10,"partantNum":10,"breed":"TROTTEUR FRANCAIS","ropePlace":10,"sex":"H","blinkers":"NONE","ownerName":"Ecurie G.E. BOUYER","trainer":{"name":"E. BOUYER","pmuName":"E. BOUYER","genyName":"Emmanuel Bouyer","canalturfId":503,"canalturfName":"E. BOUYER"},"raiserName":"Ecurie RIVAILLON","allure":"TROT","horseshoe":"ALL","jockey":{"name":"E. BOUYER","pmuName":"E. BOUYER","genyName":"Emmanuel Bouyer","canalturfName":"E. BOUYER","canalturfId":359},"robe":"079_BAI BR","musique":"DaDa6a6a6a8a(17)4a6a6a","pregnant":false,"stats":{"firstRace":false,"numberRaces":130,"wonRaces":7,"places":68,"secondPlaces":7,"thirdPlaces":12,"earnMoneyTotal":18749000,"earnMoneyFirst":6580000,"earnMoneyPlaced":12169000,"earnMoneyCurrentYear":180000,"earnMoneyPreviousYear":982000},"ecurieId":"pmu/ecurie/15032018/R3/C8:undefined","pedigree":{"father":"JASMIN DE FLORE","mother":"JEPEE"},"distance":2600,"engagement":false,"weightBeforeChanged":false,"supplement":0,"results":{"event":"NONE","position":10,"totalTimeMs":206710,"kmReducedMs":79500},"odds":{"pmu":{"lastDirect":{"typeBet":"PMU_E_SIMPLE_GAGNANT","ratio":147,"typeRatio":"DIRECT","tendancyNumber":0,"epochMs":1521127403000,"permutation":1,"favorite":false,"grossePrise":false},"lastReference":{"typeBet":"PMU_E_SIMPLE_GAGNANT","ratio":168,"typeRatio":"REFERENCE","tendancyNumber":-2.6,"epochMs":1521125412000,"permutation":1,"favorite":false,"grossePrise":false},"reference10h":{"ratio":168.1},"chronological":[{"ratio":147.4,"epoch":1521147300000},{"ratio":147.4,"epoch":1521147900000},{"ratio":147.4,"epoch":1521148500000},{"ratio":147.4,"epoch":1521149100000},{"ratio":147.4,"epoch":1521149700000},{"ratio":147.4,"epoch":1521150300000},{"ratio":147.4,"epoch":1521150900000},{"ratio":147.4,"epoch":1521151500000},{"ratio":147.4,"epoch":1521152100000},{"ratio":147.4,"epoch":1521152700000},{"ratio":147.4,"epoch":1521153300000},{"ratio":147.4,"epoch":1521153900000}]},"geny":{"lastDirect":{"ratio":186}},"zeturf":{"lastDirect":{"ratio":129.9}},"betclic":{"lastDirect":{"ratio":115.1}},"unibet":{"lastDirect":{"ratio":127.5}}},"casaques":[{"url":"https://turfinfo.pmucdn.fr/casaques/15032018/R3/C8/P10.png"},{"url":"https://media.genybet.fr/web/image/casaque/10/1001410_1.png"},{"url":"https://www.canalturf.com/interface/casaques/2018-03/167000.png","y":585,"width":55,"height":65}],"moneyWon":187490},{"raceId":"pmu_race:15032018/R3/C8","horse":{"name":"VENCEDOR","pmuName":"VENCEDOR","genyName":"VENCEDOR","genyId":2245784,"canalturfName":"VENCEDOR","canalturfId":117827},"hasSulky":true,"age":9,"partantNum":11,"breed":"TROTTEUR FRANCAIS","ropePlace":11,"sex":"M","blinkers":"NONE","ownerName":"Ecurie PARADIS","trainer":{"name":"L. PELTIER","pmuName":"L. PELTIER","genyName":"Ludovic Peltier","canalturfId":545,"canalturfName":"L. PELTIER"},"raiserName":"Ecurie LIBERTY","allure":"TROT","horseshoe":"ALL","jockey":{"name":"L. PELTIER","pmuName":"L. PELTIER","genyName":"Ludovic Peltier","canalturfName":"L. PELTIER","canalturfId":1640},"robe":"020_BAI","musique":"9a(17)5a5a1a4a2a5a6a2a","pregnant":false,"stats":{"firstRace":false,"numberRaces":89,"wonRaces":8,"places":47,"secondPlaces":12,"thirdPlaces":10,"earnMoneyTotal":20838500,"earnMoneyFirst":8155000,"earnMoneyPlaced":12683500,"earnMoneyCurrentYear":0,"earnMoneyPreviousYear":3678000},"ecurieId":"pmu/ecurie/15032018/R3/C8:undefined","pedigree":{"father":"PRODIGIOUS","mother":"NANGOON D'AR"},"distance":2600,"engagement":false,"weightBeforeChanged":false,"supplement":0,"results":{"event":"NONE","position":6,"totalTimeMs":205290,"kmReducedMs":79000},"odds":{"pmu":{"lastDirect":{"typeBet":"PMU_E_SIMPLE_GAGNANT","ratio":111,"typeRatio":"DIRECT","tendancyNumber":0,"epochMs":1521127403000,"permutation":1,"favorite":false,"grossePrise":false},"lastReference":{"typeBet":"PMU_E_SIMPLE_GAGNANT","ratio":113,"typeRatio":"REFERENCE","tendancyNumber":0.53,"epochMs":1521125412000,"permutation":1,"favorite":false,"grossePrise":false},"reference10h":{"ratio":113.2},"chronological":[{"ratio":111.2,"epoch":1521147300000},{"ratio":111.2,"epoch":1521147900000},{"ratio":111.2,"epoch":1521148500000},{"ratio":111.2,"epoch":1521149100000},{"ratio":111.2,"epoch":1521149700000},{"ratio":111.2,"epoch":1521150300000},{"ratio":111.2,"epoch":1521150900000},{"ratio":111.2,"epoch":1521151500000},{"ratio":111.2,"epoch":1521152100000},{"ratio":111.2,"epoch":1521152700000},{"ratio":111.2,"epoch":1521153300000},{"ratio":111.2,"epoch":1521153900000}]},"geny":{"lastDirect":{"ratio":81}},"zeturf":{"lastDirect":{"ratio":89.6}},"betclic":{"lastDirect":{"ratio":98.3}},"unibet":{"lastDirect":{"ratio":87.9}}},"casaques":[{"url":"https://turfinfo.pmucdn.fr/casaques/15032018/R3/C8/P11.png"},{"url":"https://media.genybet.fr/web/image/casaque/90/1041190_1.png"},{"url":"https://www.canalturf.com/interface/casaques/2018-03/167000.png","y":650,"width":55,"height":65}],"moneyWon":208385},{"raceId":"pmu_race:15032018/R3/C8","horse":{"name":"CROSS DAIRPET","pmuName":"CROSS DAIRPET","genyName":"CROSS DAIRPET","genyId":2404618,"canalturfName":"CROSS DAIRPET","canalturfId":177541},"hasSulky":true,"age":6,"partantNum":12,"breed":"TROTTEUR FRANCAIS","ropePlace":12,"sex":"M","blinkers":"NONE","ownerName":"Ecurie Michel SARDOU","trainer":{"name":"MICKAEL CORMY","pmuName":"MICKAEL CORMY","genyName":"Mickaël Cormy","canalturfId":9100,"canalturfName":"MICKAEL CORMY"},"raiserName":"M. Roger POJASEK","allure":"TROT","horseshoe":"ALL","jockey":{"name":"MICKAEL CORMY","pmuName":"MICKAEL CORMY","genyName":"Mickaël Cormy","canalturfName":"MI. CORMY","canalturfId":10722},"robe":"020_BAI","musique":"2a1a5a(17)5a4a2a1a5a8a","pregnant":false,"stats":{"firstRace":false,"numberRaces":42,"wonRaces":8,"places":25,"secondPlaces":10,"thirdPlaces":2,"earnMoneyTotal":17297000,"earnMoneyFirst":8100000,"earnMoneyPlaced":9197000,"earnMoneyCurrentYear":2050000,"earnMoneyPreviousYear":7060000},"ecurieId":"pmu/ecurie/15032018/R3/C8:undefined","pedigree":{"father":"QUAKER JET","mother":"PASSION DU CEDRE"},"distance":2600,"engagement":false,"weightBeforeChanged":false,"supplement":0,"results":{"event":"DAI"},"odds":{"pmu":{"lastDirect":{"typeBet":"PMU_E_SIMPLE_GAGNANT","ratio":16,"typeRatio":"DIRECT","tendancyNumber":0,"epochMs":1521127403000,"permutation":1,"favorite":false,"grossePrise":false},"lastReference":{"typeBet":"PMU_E_SIMPLE_GAGNANT","ratio":16,"typeRatio":"REFERENCE","tendancyNumber":-6.14,"epochMs":1521125412000,"permutation":1,"favorite":false,"grossePrise":false},"reference10h":{"ratio":16.8},"chronological":[{"ratio":16.2,"epoch":1521147300000},{"ratio":16.2,"epoch":1521147900000},{"ratio":16.2,"epoch":1521148500000},{"ratio":16.2,"epoch":1521149100000},{"ratio":16.2,"epoch":1521149700000},{"ratio":16.2,"epoch":1521150300000},{"ratio":16.2,"epoch":1521150900000},{"ratio":16.2,"epoch":1521151500000},{"ratio":16.2,"epoch":1521152100000},{"ratio":16.2,"epoch":1521152700000},{"ratio":16.2,"epoch":1521153300000},{"ratio":16.2,"epoch":1521153900000}]},"geny":{"lastDirect":{"ratio":13}},"zeturf":{"lastDirect":{"ratio":19.1}},"betclic":{"lastDirect":{"ratio":18.5}},"unibet":{"lastDirect":{"ratio":18.7}}},"casaques":[{"url":"https://turfinfo.pmucdn.fr/casaques/15032018/R3/C8/P12.png"},{"url":"https://media.genybet.fr/web/image/casaque/14/1064114_1.png"},{"url":"https://www.canalturf.com/interface/casaques/2018-03/167000.png","y":715,"width":55,"height":65}],"moneyWon":172970}],"ecuries":[{"ecurieId":"pmu/ecurie/15032018/R3/C8:A","odds":{"pmu":{"lastDirect":{"typeBet":"PMU_E_SIMPLE_GAGNANT","ratio":4.5,"typeRatio":"DIRECT","tendancyNumber":0,"epochMs":1521127403000,"favorite":false,"grossePrise":false},"lastReference":{"typeBet":"PMU_E_SIMPLE_GAGNANT","ratio":5,"typeRatio":"REFERENCE","tendancyNumber":4.16,"epochMs":1521125412000,"favorite":false,"grossePrise":false}}}}],"pays":"FRA","genyId":961212}