{"raceId":"pmu:09012018/R4/C5","raceNumber":5,"reunionNumber":4,"raceScheduledStartEpochMs":1515520920000,"raceName":"PRIX CHAMONIX                           BELGIQUE","distance":2300,"duration":172210,"ropeSide":"LEFT","fieldType":"UNKNOWN","raceCategory":"HARNESS","sexCategory":"ALL","price":{"total":5400,"first":2592,"fifth":270},"hippodromeName":"MONS (GHLIN)","fieldQuality":"DRY","photoFinishes":[{"height":217,"width":450,"url":"https://turfinfo.pmucdn.fr/infocentre/photos/arrivee/09012018R4C5/photo_arrivee_450px_width_size.jpg","originalSize":false},{"height":96,"width":200,"url":"https://turfinfo.pmucdn.fr/infocentre/photos/arrivee/09012018R4C5/photo_arrivee_200px_width_size.jpg","originalSize":false},{"height":230,"width":478,"url":"https://turfinfo.pmucdn.fr/infocentre/photos/arrivee/09012018R4C5/photo_arrivee_original_size.jpg","originalSize":true}],"startType":"AUTOSTART","raceType":"UNKNOWN","humanDescription":"PRIX CHAMONIX Course 05 Course Internationale Départ à l'Autostart 5.400 - Attelé. - 2.300 mètres. 2.592, 1.296, 540, 432, 270, 162, 108. Pour 3 à 14 ans n'ayant pas gagné 45.000.","nonPartants":[],"partants":[{"raceId":"pmu_race:09012018/R4/C5","horse":{"name":"COUCOU MON NEVEU","pmuName":"COUCOU MON NEVEU","genyName":"COUCOU MON NEVEU","genyId":2409317,"canalturfName":"COUCOU MON NEVEU","canalturfId":179809},"hasSulky":true,"age":6,"partantNum":1,"breed":"TROTTEUR FRANCAIS","ropePlace":1,"sex":"H","blinkers":"NONE","ownerName":"UNION STABLE","trainer":{"name":"UNION STABLE","pmuName":"UNION STABLE","genyName":"Union Stable","canalturfId":11217,"canalturfName":"P. LEBOUTEILLER"},"raiserName":"M. Stéphane NEVEU","allure":"TROT","horseshoe":"POST","jockey":{"name":"PIET VAN POLLAERT","pmuName":"PIET VAN POLLAERT","genyName":"Piet Van Pollaert","canalturfName":"P. VAN POLLAERT","canalturfId":464},"robe":"020_BAI","musique":"4a6a4a6a4a3a2a0a0a","pregnant":false,"stats":{"firstRace":false,"numberRaces":40,"wonRaces":1,"places":29,"secondPlaces":6,"thirdPlaces":5,"earnMoneyTotal":4330200,"earnMoneyFirst":900000,"earnMoneyPlaced":3430200,"earnMoneyCurrentYear":0,"earnMoneyPreviousYear":1057200},"ecurieId":"pmu/ecurie/09012018/R4/C5:undefined","pedigree":{"father":"QUE JE T'AIME","mother":"LAGISCA DU PORTO"},"distance":2300,"engagement":false,"weightBeforeChanged":false,"supplement":0,"results":{"event":"NONE","position":3,"totalTimeMs":173020,"kmReducedMs":75200},"odds":{"pmu":{"lastDirect":{"typeBet":"PMU_E_SIMPLE_GAGNANT","ratio":9.3,"typeRatio":"DIRECT","tendancyNumber":0,"epochMs":1515521098000,"permutation":1,"favorite":false,"grossePrise":false},"lastReference":{"typeBet":"PMU_E_SIMPLE_GAGNANT","ratio":12,"typeRatio":"REFERENCE","tendancyNumber":10.71,"epochMs":1515518713000,"permutation":1,"favorite":false,"grossePrise":false},"reference10h":{"ratio":12.4},"chronological":[{"ratio":9.3,"epoch":1515531300000},{"ratio":9.3,"epoch":1515531900000},{"ratio":9.3,"epoch":1515532500000},{"ratio":9.3,"epoch":1515533100000},{"ratio":9.3,"epoch":1515533700000},{"ratio":9.3,"epoch":1515534300000},{"ratio":9.3,"epoch":1515534900000},{"ratio":9.3,"epoch":1515535500000},{"ratio":9.3,"epoch":1515536100000},{"ratio":9.3,"epoch":1515536700000},{"ratio":9.3,"epoch":1515537300000},{"ratio":9.3,"epoch":1515537900000}]},"geny":{"lastDirect":{"ratio":16}},"zeturf":{"lastDirect":{"ratio":15}},"betclic":{"lastDirect":{"ratio":6.4}},"unibet":{"lastDirect":{"ratio":14.8}}},"casaques":[{"url":"https://turfinfo.pmucdn.fr/casaques/09012018/R4/C5/P1.png"},{"url":"https://media.genybet.fr/web/image/casaque/82/1084082_1.png"}]},{"raceId":"pmu_race:09012018/R4/C5","horse":{"name":"GOODBYE DU MOT","pmuName":"GOODBYE DU MOT","genyName":"GOODBYE DU MOT","genyId":2301215,"canalturfName":"GOODBYE DU MOT","canalturfId":176972},"hasSulky":true,"age":8,"partantNum":2,"breed":"TROTTEUR ETRANGER","ropePlace":2,"sex":"H","blinkers":"NONE","ownerName":"DENIS VOETS","trainer":{"name":"I. HUYGENS-DE WITTE","pmuName":"I. HUYGENS-DE WITTE","genyName":"Mlle Ingeborg Huygens-de Witte","canalturfId":16443,"canalturfName":"MME I. HUYGENS-DE WITTE"},"raiserName":"M. Stéphane NEVEU","allure":"TROT","horseshoe":"ALL","jockey":{"name":"MARC HUYGENS","pmuName":"MARC HUYGENS","genyName":"Marc Huygens","canalturfName":"M. HUYGENS","canalturfId":2299},"robe":"020_BAI","musique":"4a2a1a1a1a1a1a1a2a2a","pregnant":false,"stats":{"firstRace":false,"numberRaces":0,"wonRaces":0,"places":0,"secondPlaces":0,"thirdPlaces":0,"earnMoneyTotal":3985500,"earnMoneyFirst":0,"earnMoneyPlaced":0,"earnMoneyCurrentYear":0,"earnMoneyPreviousYear":0},"ecurieId":"pmu/ecurie/09012018/R4/C5:undefined","pedigree":{"father":"LOVE YOU","mother":"SOLEIL DU MOT"},"distance":2300,"engagement":false,"weightBeforeChanged":false,"supplement":0,"results":{"event":"NONE","position":7,"totalTimeMs":175080,"kmReducedMs":76100},"odds":{"pmu":{"lastDirect":{"typeBet":"PMU_E_SIMPLE_GAGNANT","ratio":3.6,"typeRatio":"DIRECT","tendancyNumber":0,"epochMs":1515521098000,"permutation":1,"favorite":true,"grossePrise":false},"lastReference":{"typeBet":"PMU_E_SIMPLE_GAGNANT","ratio":5.4,"typeRatio":"REFERENCE","tendancyNumber":-21.73,"epochMs":1515518713000,"permutation":1,"favorite":false,"grossePrise":false},"reference10h":{"ratio":5.4},"chronological":[{"ratio":3.6,"epoch":1515531300000},{"ratio":3.6,"epoch":1515531900000},{"ratio":3.6,"epoch":1515532500000},{"ratio":3.6,"epoch":1515533100000},{"ratio":3.6,"epoch":1515533700000},{"ratio":3.6,"epoch":1515534300000},{"ratio":3.6,"epoch":1515534900000},{"ratio":3.6,"epoch":1515535500000},{"ratio":3.6,"epoch":1515536100000},{"ratio":3.6,"epoch":1515536700000},{"ratio":3.6,"epoch":1515537300000},{"ratio":3.6,"epoch":1515537900000}]},"geny":{"lastDirect":{"ratio":2.4}},"zeturf":{"lastDirect":{"ratio":2.6}},"betclic":{"lastDirect":{"ratio":4}},"unibet":{"lastDirect":{"ratio":2.5}}},"casaques":[{"url":"https://turfinfo.pmucdn.fr/casaques/09012018/R4/C5/P2.png"},{"url":"https://media.genybet.fr/web/image/casaque/67/1109967_1.png"}]},{"raceId":"pmu_race:09012018/R4/C5","horse":{"name":"BALZAN FOR CLARA","pmuName":"BALZAN FOR CLARA","genyName":"BALZAN FOR CLARA","genyId":2380539,"canalturfName":"BALZAN FOR CLARA","canalturfId":171647},"hasSulky":true,"age":7,"partantNum":3,"breed":"TROTTEUR FRANCAIS","ropePlace":3,"sex":"H","blinkers":"NONE","ownerName":"GÉRARD DE DRYVER","trainer":{"name":"GÉRARD DE DRYVER","pmuName":"GÉRARD DE DRYVER","genyName":"Gérard de Dryver","canalturfId":10400,"canalturfName":"GODEY P."},"raiserName":"M. Gérard DE DRYVER","allure":"TROT","horseshoe":"ALL","jockey":{"name":"JOSEPH VERBEECK","pmuName":"JOSEPH VERBEECK","genyName":"Jos Verbeeck","canalturfName":"J. VERBEECK","canalturfId":482},"robe":"005_AL FON","musique":"3a0a8a0a3a","pregnant":false,"stats":{"firstRace":false,"numberRaces":51,"wonRaces":0,"places":23,"secondPlaces":4,"thirdPlaces":5,"earnMoneyTotal":3761000,"earnMoneyFirst":0,"earnMoneyPlaced":3761000,"earnMoneyCurrentYear":0,"earnMoneyPreviousYear":462000},"ecurieId":"pmu/ecurie/09012018/R4/C5:undefined","pedigree":{"father":"QUALYPSO JIEL","mother":"EQUIDYNE FOR CLARA"},"distance":2300,"engagement":false,"weightBeforeChanged":false,"supplement":0,"results":{"event":"DAI"},"odds":{"pmu":{"lastDirect":{"typeBet":"PMU_E_SIMPLE_GAGNANT","ratio":20,"typeRatio":"DIRECT","tendancyNumber":0,"epochMs":1515521098000,"permutation":1,"favorite":false,"grossePrise":false},"lastReference":{"typeBet":"PMU_E_SIMPLE_GAGNANT","ratio":18,"typeRatio":"REFERENCE","tendancyNumber":13.92,"epochMs":1515518713000,"permutation":1,"favorite":false,"grossePrise":false},"reference10h":{"ratio":18},"chronological":[{"ratio":20,"epoch":1515531300000},{"ratio":20,"epoch":1515531900000},{"ratio":20,"epoch":1515532500000},{"ratio":20,"epoch":1515533100000},{"ratio":20,"epoch":1515533700000},{"ratio":20,"epoch":1515534300000},{"ratio":20,"epoch":1515534900000},{"ratio":20,"epoch":1515535500000},{"ratio":20,"epoch":1515536100000},{"ratio":20,"epoch":1515536700000},{"ratio":20,"epoch":1515537300000},{"ratio":20,"epoch":1515537900000}]},"geny":{"lastDirect":{"ratio":21}},"zeturf":{"lastDirect":{"ratio":20.5}},"betclic":{"lastDirect":{"ratio":16}},"unibet":{"lastDirect":{"ratio":21.2}}},"casaques":[{"url":"https://turfinfo.pmucdn.fr/casaques/09012018/R4/C5/P3.png"},{"url":"https://media.genybet.fr/web/image/casaque/19/1002719_1.png"}]},{"raceId":"pmu_race:09012018/R4/C5","horse":{"name":"PROUD OF MY FACE","pmuName":"PROUD OF MY FACE","genyName":"PROUD OF MY FACE","genyId":2397788,"canalturfName":"PROUD OF MY FACE","canalturfId":219734},"hasSulky":true,"age":6,"partantNum":4,"breed":"TROTTEUR ETRANGER","ropePlace":4,"sex":"F","blinkers":"NONE","ownerName":"NON STOP STABLES","trainer":{"name":"GUIDO LAUREYS","pmuName":"GUIDO LAUREYS","genyName":"Guido Laureys","canalturfId":1384,"canalturfName":"GUIDO LAUREYS"},"allure":"TROT","horseshoe":"ALL","jockey":{"name":"GREGORY CELIS","pmuName":"GREGORY CELIS","genyName":"Grégory Celis","canalturfName":"G. CELIS","canalturfId":2317},"robe":"020_BAI","musique":"3a6a4a1a0a3a6a3a3aDm","pregnant":false,"stats":{"firstRace":false,"numberRaces":1,"wonRaces":0,"places":0,"secondPlaces":0,"thirdPlaces":0,"earnMoneyTotal":2924200,"earnMoneyFirst":0,"earnMoneyPlaced":0,"earnMoneyCurrentYear":0,"earnMoneyPreviousYear":0},"ecurieId":"pmu/ecurie/09012018/R4/C5:undefined","pedigree":{"father":"GIFT KRONOS","mother":"ARMBRO DAFFODIL"},"distance":2300,"engagement":false,"weightBeforeChanged":false,"supplement":0,"results":{"event":"NONE","position":1,"totalTimeMs":172210,"kmReducedMs":74900},"odds":{"pmu":{"lastDirect":{"typeBet":"PMU_E_SIMPLE_GAGNANT","ratio":11,"typeRatio":"DIRECT","tendancyNumber":0,"epochMs":1515521098000,"permutation":1,"favorite":false,"grossePrise":false},"lastReference":{"typeBet":"PMU_E_SIMPLE_GAGNANT","ratio":15,"typeRatio":"REFERENCE","tendancyNumber":-8.82,"epochMs":1515518713000,"permutation":1,"favorite":false,"grossePrise":false},"reference10h":{"ratio":15.5},"chronological":[{"ratio":11.3,"epoch":1515531300000},{"ratio":11.3,"epoch":1515531900000},{"ratio":11.3,"epoch":1515532500000},{"ratio":11.3,"epoch":1515533100000},{"ratio":11.3,"epoch":1515533700000},{"ratio":11.3,"epoch":1515534300000},{"ratio":11.3,"epoch":1515534900000},{"ratio":11.3,"epoch":1515535500000},{"ratio":11.3,"epoch":1515536100000},{"ratio":11.3,"epoch":1515536700000},{"ratio":11.3,"epoch":1515537300000},{"ratio":11.3,"epoch":1515537900000}]},"geny":{"lastDirect":{"ratio":12}},"zeturf":{"lastDirect":{"ratio":20.3}},"betclic":{"lastDirect":{"ratio":29.5}},"unibet":{"lastDirect":{"ratio":21}}},"casaques":[{"url":"https://turfinfo.pmucdn.fr/casaques/09012018/R4/C5/P4.png"},{"url":"https://media.genybet.fr/web/image/casaque/77/1087677_1.png"}]},{"raceId":"pmu_race:09012018/R4/C5","horse":{"name":"BEST DE VERRIERES","pmuName":"BEST DE VERRIERES","genyName":"BEST DE VERRIERES","genyId":2437477,"canalturfName":"BEST DE VERRIERES","canalturfId":195020},"hasSulky":true,"age":7,"partantNum":5,"breed":"TROTTEUR FRANCAIS","ropePlace":5,"sex":"H","blinkers":"NONE","ownerName":"JONATHAN LEROYER","trainer":{"name":"JONATHAN LEROYER","pmuName":"JONATHAN LEROYER","genyName":"Jonathan Leroyer","canalturfId":10870,"canalturfName":"F. HENDRICKX"},"raiserName":"M. Philippe LEROYER","allure":"TROT","horseshoe":"POST","jockey":{"name":"OLIVIER BIZOUX","pmuName":"OLIVIER BIZOUX","genyName":"Olivier Bizoux","canalturfName":"O. BIZOUX","canalturfId":496},"robe":"001_ALEZAN","musique":"DaDaDa3a8a","pregnant":false,"stats":{"firstRace":false,"numberRaces":40,"wonRaces":0,"places":16,"secondPlaces":3,"thirdPlaces":5,"earnMoneyTotal":2751500,"earnMoneyFirst":0,"earnMoneyPlaced":2751500,"earnMoneyCurrentYear":0,"earnMoneyPreviousYear":239500},"ecurieId":"pmu/ecurie/09012018/R4/C5:undefined","pedigree":{"father":"NORMAN JET","mother":"OKALINE"},"distance":2300,"engagement":false,"weightBeforeChanged":false,"supplement":0,"results":{"event":"NONE","position":6,"totalTimeMs":174510,"kmReducedMs":75900},"odds":{"pmu":{"lastDirect":{"typeBet":"PMU_E_SIMPLE_GAGNANT","ratio":53,"typeRatio":"DIRECT","tendancyNumber":0,"epochMs":1515521098000,"permutation":1,"favorite":false,"grossePrise":false},"lastReference":{"typeBet":"PMU_E_SIMPLE_GAGNANT","ratio":25,"typeRatio":"REFERENCE","tendancyNumber":21.63,"epochMs":1515518713000,"permutation":1,"favorite":false,"grossePrise":false},"reference10h":{"ratio":25.3},"chronological":[{"ratio":53.9,"epoch":1515531300000},{"ratio":53.9,"epoch":1515531900000},{"ratio":53.9,"epoch":1515532500000},{"ratio":53.9,"epoch":1515533100000},{"ratio":53.9,"epoch":1515533700000},{"ratio":53.9,"epoch":1515534300000},{"ratio":53.9,"epoch":1515534900000},{"ratio":53.9,"epoch":1515535500000},{"ratio":53.9,"epoch":1515536100000},{"ratio":53.9,"epoch":1515536700000},{"ratio":53.9,"epoch":1515537300000},{"ratio":53.9,"epoch":1515537900000}]},"geny":{"lastDirect":{"ratio":90}},"zeturf":{"lastDirect":{"ratio":60.1}},"betclic":{"lastDirect":{"ratio":36.3}},"unibet":{"lastDirect":{"ratio":58.4}}},"casaques":[{"url":"https://turfinfo.pmucdn.fr/casaques/09012018/R4/C5/P5.png"},{"url":"https://media.genybet.fr/web/image/casaque/82/1075882_1.png"}]},{"raceId":"pmu_race:09012018/R4/C5","horse":{"name":"FORLAN","pmuName":"FORLAN","genyName":"FORLAN","genyId":2257183,"canalturfName":"FORLAN","canalturfId":150864},"hasSulky":true,"age":9,"partantNum":6,"breed":"TROTTEUR ETRANGER","ropePlace":6,"sex":"H","blinkers":"NONE","ownerName":"LUC VANDERMASSEN","trainer":{"name":"I. HUYGENS-DE WITTE","pmuName":"I. HUYGENS-DE WITTE","genyName":"Mlle Ingeborg Huygens-de Witte","canalturfId":16443,"canalturfName":"I HUYGENS-DE WITTE"},"allure":"TROT","horseshoe":"ALL","jockey":{"name":"MME HANNA HUYGENS","pmuName":"MME HANNA HUYGENS","genyName":"Mlle Hanna Huygens","canalturfName":"MLLE H. HUYGENS","canalturfId":10176},"robe":"020_BAI","musique":"1a1a8a1a1a2a3a4a6a1a","pregnant":false,"stats":{"firstRace":false,"numberRaces":0,"wonRaces":0,"places":0,"secondPlaces":0,"thirdPlaces":0,"earnMoneyTotal":4030800,"earnMoneyFirst":0,"earnMoneyPlaced":0,"earnMoneyCurrentYear":0,"earnMoneyPreviousYear":0},"ecurieId":"pmu/ecurie/09012018/R4/C5:undefined","pedigree":{"father":"ALIEN CHIP","mother":"JACOBINE VG"},"distance":2300,"engagement":false,"weightBeforeChanged":false,"supplement":0,"results":{"event":"NONE","position":2,"totalTimeMs":172920,"kmReducedMs":75200},"odds":{"pmu":{"lastDirect":{"typeBet":"PMU_E_SIMPLE_GAGNANT","ratio":9.5,"typeRatio":"DIRECT","tendancyNumber":0,"epochMs":1515521098000,"permutation":1,"favorite":false,"grossePrise":false},"lastReference":{"typeBet":"PMU_E_SIMPLE_GAGNANT","ratio":8,"typeRatio":"REFERENCE","tendancyNumber":6.66,"epochMs":1515518713000,"permutation":1,"favorite":false,"grossePrise":false},"reference10h":{"ratio":8},"chronological":[{"ratio":9.5,"epoch":1515531300000},{"ratio":9.5,"epoch":1515531900000},{"ratio":9.5,"epoch":1515532500000},{"ratio":9.5,"epoch":1515533100000},{"ratio":9.5,"epoch":1515533700000},{"ratio":9.5,"epoch":1515534300000},{"ratio":9.5,"epoch":1515534900000},{"ratio":9.5,"epoch":1515535500000},{"ratio":9.5,"epoch":1515536100000},{"ratio":9.5,"epoch":1515536700000},{"ratio":9.5,"epoch":1515537300000},{"ratio":9.5,"epoch":1515537900000}]},"geny":{"lastDirect":{"ratio":19}},"zeturf":{"lastDirect":{"ratio":10.8}},"betclic":{"lastDirect":{"ratio":20.3}},"unibet":{"lastDirect":{"ratio":10.5}}},"casaques":[{"url":"https://turfinfo.pmucdn.fr/casaques/09012018/R4/C5/P6.png"},{"url":"https://media.genybet.fr/web/image/casaque/19/1094519_1.png"}]},{"raceId":"pmu_race:09012018/R4/C5","horse":{"name":"JACK LJ","pmuName":"JACK LJ","genyName":"JACK LJ","genyId":2449851,"canalturfName":"JACK LJ","canalturfId":217129},"hasSulky":true,"age":5,"partantNum":7,"breed":"TROTTEUR ETRANGER","ropePlace":7,"sex":"H","blinkers":"NONE","ownerName":"ECURIE LJ","trainer":{"name":"CARINE DE SOETE","pmuName":"CARINE DE SOETE","genyName":"Mme Carine de Soete","canalturfId":1031,"canalturfName":"ECURIE LJ"},"allure":"TROT","horseshoe":"NONE","jockey":{"name":"RIK DEPUYDT","pmuName":"RIK DEPUYDT","genyName":"Rik Depuydt","canalturfName":"RIK DEPUYDT","canalturfId":2671},"robe":"020_BAI","musique":"1a1a2a2a3a4a5a3a3a2a","pregnant":false,"stats":{"firstRace":false,"numberRaces":0,"wonRaces":0,"places":0,"secondPlaces":0,"thirdPlaces":0,"earnMoneyTotal":3698300,"earnMoneyFirst":0,"earnMoneyPlaced":0,"earnMoneyCurrentYear":0,"earnMoneyPreviousYear":0},"ecurieId":"pmu/ecurie/09012018/R4/C5:undefined","pedigree":{"father":"OTELLO PIERJI","mother":"TELL ME MORE"},"distance":2300,"engagement":false,"weightBeforeChanged":false,"supplement":0,"results":{"event":"NONE","position":4,"totalTimeMs":173400,"kmReducedMs":75400},"odds":{"pmu":{"lastDirect":{"typeBet":"PMU_E_SIMPLE_GAGNANT","ratio":3.9,"typeRatio":"DIRECT","tendancyNumber":0,"epochMs":1515521098000,"permutation":1,"favorite":false,"grossePrise":false},"lastReference":{"typeBet":"PMU_E_SIMPLE_GAGNANT","ratio":4.4,"typeRatio":"REFERENCE","tendancyNumber":15.78,"epochMs":1515518713000,"permutation":1,"favorite":false,"grossePrise":false},"reference10h":{"ratio":4.4},"chronological":[{"ratio":3.9,"epoch":1515531300000},{"ratio":3.9,"epoch":1515531900000},{"ratio":3.9,"epoch":1515532500000},{"ratio":3.9,"epoch":1515533100000},{"ratio":3.9,"epoch":1515533700000},{"ratio":3.9,"epoch":1515534300000},{"ratio":3.9,"epoch":1515534900000},{"ratio":3.9,"epoch":1515535500000},{"ratio":3.9,"epoch":1515536100000},{"ratio":3.9,"epoch":1515536700000},{"ratio":3.9,"epoch":1515537300000},{"ratio":3.9,"epoch":1515537900000}]},"geny":{"lastDirect":{"ratio":4.6}},"zeturf":{"lastDirect":{"ratio":3.3}},"betclic":{"lastDirect":{"ratio":3.2}},"unibet":{"lastDirect":{"ratio":3.2}}},"casaques":[{"url":"https://turfinfo.pmucdn.fr/casaques/09012018/R4/C5/P7.png"},{"url":"https://media.genybet.fr/web/image/casaque/06/1070606_1.png"}]},{"raceId":"pmu_race:09012018/R4/C5","horse":{"name":"ERWIN LOBELL","pmuName":"ERWIN LOBELL","genyName":"ERWIN LOBELL","genyId":2382919,"canalturfName":"ERWIN LOBELL","canalturfId":195198},"hasSulky":true,"age":7,"partantNum":8,"breed":"TROTTEUR ETRANGER","ropePlace":8,"sex":"M","blinkers":"NONE","ownerName":"BV VAN BELLEN BEHEER","trainer":{"name":"H.W. LANGEWEG JR.","pmuName":"H.W. LANGEWEG JR.","genyName":"Hugo W. Langeweg Jr.","canalturfId":2967,"canalturfName":"H.W. LANGEWEG JR."},"allure":"TROT","horseshoe":"ALL","jockey":{"name":"H.W. LANGEWEG JR.","pmuName":"H.W. LANGEWEG JR.","genyName":"Hugo W. Langeweg Jr.","canalturfName":"H. W. LANGEWEG JR.","canalturfId":3063},"robe":"020_BAI","musique":"4a1a1a5a7a","pregnant":false,"stats":{"firstRace":false,"numberRaces":2,"wonRaces":0,"places":2,"secondPlaces":0,"thirdPlaces":0,"earnMoneyTotal":4493000,"earnMoneyFirst":0,"earnMoneyPlaced":222000,"earnMoneyCurrentYear":0,"earnMoneyPreviousYear":22000},"ecurieId":"pmu/ecurie/09012018/R4/C5:undefined","pedigree":{"father":"GOETMALS WOOD","mother":"WICHITA RIVER"},"distance":2300,"engagement":false,"weightBeforeChanged":false,"supplement":0,"results":{"event":"NONE","position":5,"totalTimeMs":173420,"kmReducedMs":75400},"odds":{"pmu":{"lastDirect":{"typeBet":"PMU_E_SIMPLE_GAGNANT","ratio":4,"typeRatio":"DIRECT","tendancyNumber":0,"epochMs":1515521098000,"permutation":1,"favorite":false,"grossePrise":false},"lastReference":{"typeBet":"PMU_E_SIMPLE_GAGNANT","ratio":2.8,"typeRatio":"REFERENCE","tendancyNumber":-6.66,"epochMs":1515518713000,"permutation":1,"favorite":true,"grossePrise":false},"reference10h":{"ratio":2.8},"chronological":[{"ratio":4,"epoch":1515531300000},{"ratio":4,"epoch":1515531900000},{"ratio":4,"epoch":1515532500000},{"ratio":4,"epoch":1515533100000},{"ratio":4,"epoch":1515533700000},{"ratio":4,"epoch":1515534300000},{"ratio":4,"epoch":1515534900000},{"ratio":4,"epoch":1515535500000},{"ratio":4,"epoch":1515536100000},{"ratio":4,"epoch":1515536700000},{"ratio":4,"epoch":1515537300000},{"ratio":4,"epoch":1515537900000}]},"geny":{"lastDirect":{"ratio":3.5}},"zeturf":{"lastDirect":{"ratio":5.3}},"betclic":{"lastDirect":{"ratio":4}},"unibet":{"lastDirect":{"ratio":5.1}}},"casaques":[{"url":"https://turfinfo.pmucdn.fr/casaques/09012018/R4/C5/P8.png"},{"url":"https://media.genybet.fr/web/image/casaque/64/1019164_1.png"}]},{"raceId":"pmu_race:09012018/R4/C5","horse":{"name":"AXEL DE GRAVELLE","pmuName":"AXEL DE GRAVELLE","genyName":"AXEL DE GRAVELLE","genyId":2360723,"canalturfName":"AXEL DE GRAVELLE","canalturfId":149844},"hasSulky":true,"age":8,"partantNum":9,"breed":"TROTTEUR FRANCAIS","ropePlace":9,"sex":"H","blinkers":"NONE","ownerName":"MARC KINDERMANS","trainer":{"name":"KRISTOF DEPUYDT","pmuName":"KRISTOF DEPUYDT","genyName":"Kristof Depuydt","canalturfId":1495,"canalturfName":"DRIES DEVOLDER"},"raiserName":"Mme Yvette HOUDAYER","allure":"TROT","horseshoe":"ALL","jockey":{"name":"KRISTOF DEPUYDT","pmuName":"KRISTOF DEPUYDT","genyName":"Kristof Depuydt","canalturfName":"K. DEPUYDT","canalturfId":1480},"robe":"005_AL FON","musique":"DaDa4a5a2aDaDa0a3a7a","pregnant":false,"stats":{"firstRace":false,"numberRaces":54,"wonRaces":8,"places":24,"secondPlaces":6,"thirdPlaces":5,"earnMoneyTotal":2706800,"earnMoneyFirst":1386000,"earnMoneyPlaced":1320800,"earnMoneyCurrentYear":0,"earnMoneyPreviousYear":494800},"ecurieId":"pmu/ecurie/09012018/R4/C5:undefined","pedigree":{"father":"LOOK DE STAR","mother":"JERSEY BLUE"},"distance":2300,"engagement":false,"weightBeforeChanged":false,"supplement":0,"results":{"event":"NONE","position":8,"totalTimeMs":178740,"kmReducedMs":77700},"odds":{"pmu":{"lastDirect":{"typeBet":"PMU_E_SIMPLE_GAGNANT","ratio":57,"typeRatio":"DIRECT","tendancyNumber":0,"epochMs":1515521098000,"permutation":1,"favorite":false,"grossePrise":false},"lastReference":{"typeBet":"PMU_E_SIMPLE_GAGNANT","ratio":27,"typeRatio":"REFERENCE","tendancyNumber":-3.46,"epochMs":1515518713000,"permutation":1,"favorite":false,"grossePrise":false},"reference10h":{"ratio":27.9},"chronological":[{"ratio":57.4,"epoch":1515531300000},{"ratio":57.4,"epoch":1515531900000},{"ratio":57.4,"epoch":1515532500000},{"ratio":57.4,"epoch":1515533100000},{"ratio":57.4,"epoch":1515533700000},{"ratio":57.4,"epoch":1515534300000},{"ratio":57.4,"epoch":1515534900000},{"ratio":57.4,"epoch":1515535500000},{"ratio":57.4,"epoch":1515536100000},{"ratio":57.4,"epoch":1515536700000},{"ratio":57.4,"epoch":1515537300000},{"ratio":57.4,"epoch":1515537900000}]},"geny":{"lastDirect":{"ratio":32}},"zeturf":{"lastDirect":{"ratio":51.2}},"betclic":{"lastDirect":{"ratio":16}},"unibet":{"lastDirect":{"ratio":51}}},"casaques":[{"url":"https://turfinfo.pmucdn.fr/casaques/09012018/R4/C5/P9.png"},{"url":"https://media.genybet.fr/web/image/casaque/74/1072974_1.png"}]}],"ecuries":[],"pays":"BEL","raceGeoRange":"INTERNATIONAL","genyId":952066}